{"cameraMode":{"drawMode":3,"name":"Shadow Cascades","section":"Miscellaneous"},"sceneLighting":false,"audioPlay":false,"sceneViewState":{"m_AlwaysRefresh":false,"showFog":true,"showSkybox":false,"showFlares":true,"showImageEffects":true,"showParticleSystems":true,"showVisualEffectGraphs":true,"m_FxEnabled":false},"in2DMode":false,"pivot":{"x":-6.236850738525391,"y":1.7976568937301636,"z":-5.318574905395508},"rotation":{"x":0.06240027770400047,"y":0.9331854581832886,"z":-0.1989014744758606,"w":0.29276323318481448},"size":36.2216682434082,"orthographic":false}