{"cameraMode":{"drawMode":3,"name":"Shadow Cascades","section":"Miscellaneous"},"sceneLighting":true,"audioPlay":false,"sceneViewState":{"m_AlwaysRefresh":false,"showFog":true,"showSkybox":true,"showFlares":true,"showImageEffects":true,"showParticleSystems":true,"showVisualEffectGraphs":true,"m_FxEnabled":false},"in2DMode":false,"pivot":{"x":-158.5313720703125,"y":-254.69815063476563,"z":-536.1541748046875},"rotation":{"x":0.07465315610170365,"y":0.909871518611908,"z":-0.3632872700691223,"w":0.18675202131271363},"size":546.0824584960938,"orthographic":false}